voxai/__init__.py
voxai/cli.py
voxai/config.py
voxai/core.py
voxai/electron/icon.png
voxai/electron/index.html
voxai/electron/main.js
voxai/electron/package.json
voxai/electron/preload.js
voxai-0.4.1.dist-info/METADATA
voxai-0.4.1.dist-info/WHEEL
voxai-0.4.1.dist-info/entry_points.txt
voxai-0.4.1.dist-info/top_level.txt
voxai-0.4.1.dist-info/RECORD
