Metadata-Version: 2.4
Name: voxai
Version: 0.4.1
Summary: Voice-driven AI assistant with OpenAI GPT-4o integration and enhanced dark theme UI for improved readability.
Author-email: "Ravi (Robbie) Tiwari" <rtiwariops@gmail.com>
License: MIT
Project-URL: Homepage, https://github.com/rtiwariops/voxai
Project-URL: Documentation, https://voxai.readthedocs.io/
Project-URL: Repository, https://github.com/rtiwariops/voxai
Project-URL: Bug Tracker, https://github.com/rtiwariops/voxai/issues
Classifier: Programming Language :: Python :: 3
Classifier: License :: OSI Approved :: MIT License
Classifier: Operating System :: OS Independent
Classifier: Topic :: Scientific/Engineering :: Artificial Intelligence
Classifier: Topic :: Multimedia :: Sound/Audio :: Capture/Recording
Classifier: Topic :: Software Development :: User Interfaces
Classifier: Intended Audience :: Developers
Classifier: Intended Audience :: End Users/Desktop
Requires-Python: >=3.7
Requires-Dist: sounddevice
Requires-Dist: faster_whisper
Requires-Dist: openai
Requires-Dist: python-dotenv
